dv_pyclient/__init__.py
dv_pyclient/cli.py
dv_pyclient/util.py
dv_pyclient/auth/__init__.py
dv_pyclient/auth/auth.py
dv_pyclient/client/__init__.py
dv_pyclient/client/exec.py
dv_pyclient/client/publish.py
dv_pyclient/dataframe/__init__.py
dv_pyclient/dataframe/util.py
dv_pyclient/dataload/__init__.py
dv_pyclient/dataload/_domain.py
dv_pyclient/dataload/validate.py
dv_pyclient/grpc/__init__.py
dv_pyclient/grpc/converters.py
dv_pyclient/grpc/dataSources_pb2.py
dv_pyclient/grpc/dataSources_pb2_grpc.py
dv_pyclient/grpc/dataframe_utils.py
dv_pyclient/grpc/scalapb_pb2.py
dv_pyclient/grpc/scalapb_pb2_grpc.py
dv_pyclient/grpc/util.py
dv_pyclient/server/__init__.py
dv_pyclient/server/data_frame_servicer.py
dv_pyclient-0.7.2.dist-info/LICENSE
dv_pyclient-0.7.2.dist-info/METADATA
dv_pyclient-0.7.2.dist-info/WHEEL
dv_pyclient-0.7.2.dist-info/entry_points.txt
dv_pyclient-0.7.2.dist-info/top_level.txt
dv_pyclient-0.7.2.dist-info/RECORD
