Metadata-Version: 2.1
Name: dv-pyclient
Version: 0.7.2
Summary: Python libraries for Datavore. Auth, Exec, Publish, gRPC, ....
Home-page: https://github.com/datavore-labs/dv-pyclient
Author: Datavore Labs
Author-email: info@datavorelabs.com
License: MIT license
Keywords: dv_pyclient
Platform: UNKNOWN
Classifier: Development Status :: 2 - Pre-Alpha
Classifier: Intended Audience :: Developers
Classifier: License :: OSI Approved :: MIT License
Classifier: Natural Language :: English
Classifier: Programming Language :: Python :: 3
Classifier: Programming Language :: Python :: 3.5
Classifier: Programming Language :: Python :: 3.6
Classifier: Programming Language :: Python :: 3.7
Classifier: Programming Language :: Python :: 3.8
Requires-Python: >=3.5
Requires-Dist: Click (>=7.0)
Requires-Dist: pandas
Requires-Dist: numpy
Requires-Dist: PyJWT
Requires-Dist: requests
Requires-Dist: ndjson
Requires-Dist: grpcio (>=1.27.2)
Requires-Dist: protobuf
